{
  "abbr": "NWU",
  "applicationPeriod": {
    "opens": "1 June 2026",
    "closes": "31 August 2026",
    "intakeYear": 2027
  },
  "applicationFee": 150,
  "feeWaiver": false,
  "minimumAPS": 20,
  "apsNote": "Earlier closing than most universities. Potchefstroom is most competitive.",
  "applyUrl": "https://studies.nwu.ac.za/undergraduate-studies/application",
  "requiredDocuments": [
    "Certified copy of South African ID or valid passport",
    "Certified copy of matric certificate or statement of results",
    "Grade 11 and Grade 12 school report",
    "Proof of residence (not older than 3 months)",
    "Completed application form"
  ],
  "internationalStudents": {
    "accepted": true,
    "note": "International applicants require SAQA evaluation of qualifications."
  },
  "_datesUpdated": "2026-06-21 (web-verified, 2027 intake)",
  "_verified": {
    "date": "2026-06-21",
    "method": "official-site-research",
    "fields": {
      "website": {
        "confidence": "high",
        "source": "https://www.nwu.ac.za/"
      },
      "applyUrl": {
        "confidence": "high",
        "source": "https://studies.nwu.ac.za/undergraduate-studies/application"
      },
      "prospectusUrl": {
        "confidence": "medium",
        "source": "https://studies.nwu.ac.za/undergraduate-studies/fields-study-2027"
      },
      "applicationOpens": {
        "confidence": "high",
        "source": "https://studies.nwu.ac.za/undergraduate-studies/application"
      },
      "applicationCloses": {
        "confidence": "high",
        "source": "https://studies.nwu.ac.za/undergraduate-studies/application",
        "note": "CORRECTION from 30 Sep; selection courses close 30 June"
      },
      "applicationFee": {
        "confidence": "high",
        "source": "https://studies.nwu.ac.za/undergraduate-studies/application",
        "note": "CORRECTION from R100; new R150 fee for 2027 (intl R600)"
      },
      "minimumAPS": {
        "confidence": "medium",
        "source": "https://studies.nwu.ac.za/undergraduate-studies/application",
        "note": "absolute min 18"
      },
      "city": {
        "confidence": "high",
        "source": "https://www.nwu.ac.za/"
      },
      "province": {
        "confidence": "high",
        "source": "https://www.nwu.ac.za/"
      },
      "founded": {
        "confidence": "high",
        "source": "https://www.nwu.ac.za/"
      },
      "students": {
        "confidence": "medium",
        "source": "https://www.nwu.ac.za/",
        "note": "CORRECTION from 65000; ~55096 per Quick Stats"
      },
      "type": {
        "confidence": "high",
        "source": "https://www.nwu.ac.za/"
      },
      "faculties": {
        "confidence": "high",
        "source": "https://studies.nwu.ac.za/studies/our-faculties",
        "note": "CORRECTION: 8 faculties, fixed names"
      }
    }
  },
  "internationalFee": "R600",
  "apsSystem": "APS /42",
  "apsRange": "18–36",
  "healthSciencesCloses": "30 June 2026",
  "_researchVerified": {
    "date": "2026-06-24",
    "intake": 2027,
    "confidence": "high",
    "sources": [
      "https://studies.nwu.ac.za/undergraduate-studies/application",
      "https://studies.nwu.ac.za/studies/apply",
      "https://studies.nwu.ac.za/undergraduate-studies/fields-study-2027",
      "https://studies.nwu.ac.za/undergraduate-studies/fields-study",
      "https://studies.nwu.ac.za/undergraduate-studies/fields-study-economic",
      "https://studies.nwu.ac.za/undergraduate-studies/education-2027"
    ],
    "flags": [
      "applicationOpens: 2027 cycle opened 1 June 2026 per official NWU news — confirm 2028-intake opening date when announced",
      "healthSciencesCloses: 30 June closing applies to multiple selection-course programmes (Pharmacy, Consumer Studies, Social Work, Biokinetics, Dietetics, Occupational Hygiene) — not a single named 'Health Sciences' faculty deadline",
      "students: 56,000 figure from Wikipedia; official Quick Stats PDF could not be parsed to verify exact current headcount",
      "BCom Statistics minimum APS range is 20–24 (extended option 20); flagged as range rather than single value",
      "BCom Economic Sciences minimum APS range is 20–26 depending on specialization",
      "BAdmin Human Resources Management minimum APS range is 21–23 depending on campus",
      "BSc (general) APS 26 covers multiple specializations; some extended versions accept APS 24–28",
      "Desmond Tutu School of Medicine under construction — first MBChB enrolment not until 2028, so no Medicine programme listed"
    ]
  }
}